newlandface/__init__.py
newlandface/nlface.py
newlandface/basemodels/DeepID.py
newlandface/basemodels/DlibResNet.py
newlandface/basemodels/Facenet.py
newlandface/basemodels/FbDeepFace.py
newlandface/basemodels/OpenFace.py
newlandface/basemodels/VGGFace.py
newlandface/basemodels/__init__.py
newlandface/commons/__init__.py
newlandface/commons/distance.py
newlandface/commons/functions.py
newlandface/commons/realtime.py
newlandface/extendedmodels/Age.py
newlandface/extendedmodels/Emotion.py
newlandface/extendedmodels/Gender.py
newlandface/extendedmodels/Race.py
newlandface/extendedmodels/__init__.py
newlandface/models/__init__.py
newlandface-1.0.3.dist-info/LICENSE
newlandface-1.0.3.dist-info/METADATA
newlandface-1.0.3.dist-info/WHEEL
newlandface-1.0.3.dist-info/top_level.txt
newlandface-1.0.3.dist-info/RECORD
