Metadata-Version: 2.1
Name: newlandface
Version: 1.0.3
Summary: A Lightweight Face Detection and Facial Attribute Analysis Framework (Age, Gender, Emotion) for Python
Home-page: https://github.com/fjndfazp/newlandface
Author: fjndfazp
Author-email: gyyzp@qq.com
License: UNKNOWN
Platform: UNKNOWN
Classifier: Programming Language :: Python :: 3
Classifier: License :: OSI Approved :: MIT License
Classifier: Operating System :: OS Independent
Requires-Python: >=3.5.5
Requires-Dist: numpy (>=1.14.0)
Requires-Dist: pandas (>=0.23.4)
Requires-Dist: gdown (>=3.10.1)
Requires-Dist: tqdm (>=4.30.0)
Requires-Dist: Pillow (>=5.2.0)
Requires-Dist: opencv-python (>=3.4.4)
Requires-Dist: tensorflow (>=1.9.0)
Requires-Dist: keras (>=2.2.0)
Requires-Dist: Flask (>=1.1.2)
Requires-Dist: mtcnn (>=0.1.0)
